{
  "自动泊车入位": "Автопарковка",
  "上坡辅助": "Помощь при трогании в гору",
  "定速巡航": "Круиз-контроль",
  "自适应巡航": "Адаптивный круиз-контроль",
  "全速自适应巡航": "Адаптивный круиз-контроль (весь диапазон скоростей)",
  "L2级辅助驾驶": "Ассистент вождения уровня L2",
  "自动驾驶辅助": "Ассистент автоматизированного вождения",
  "自动变道辅助": "Ассистент автоматической смены полосы",
  "车道居中保持": "Удержание по центру полосы",
  "车道偏离预警": "Предупреждение о выходе из полосы",
  "车道偏离预警系统": "Система предупреждения о выходе из полосы",
  "车道保持辅助": "Удержание в полосе",
  "车道保持系统": "Система удержания в полосе",
  "前方碰撞预警": "Предупреждение о фронтальном столкновении",
  "后方碰撞预警": "Предупреждение о столкновении сзади",
  "开门预警": "Предупреждение при открытии двери",
  "并线辅助": "Контроль слепых зон",
  "并线辅助系统": "Система контроля слепых зон",
  "盲点监测": "Мониторинг слепых зон",
  "主动安全预警系统": "Система активной безопасности",
  "主动刹车": "Система автоматического торможения",
  "主动刹车/主动安全系统": "Активное торможение / активная безопасность",
  "自动紧急制动": "Автоматическое экстренное торможение",
  "道路交通标识识别": "Распознавание дорожных знаков",
  "疲劳驾驶提示": "Контроль усталости водителя",
  "疲劳驾驶提醒": "Предупреждение об усталости водителя",
  "DOW开门预警": "Предупреждение о помехе при открытии двери (DOW)",
  "前驻车雷达": "Передний парктроник",
  "后驻车雷达": "Задний парктроник",
  "前后驻车雷达": "Передний и задний парктроник",
  "驻车雷达": "Парктроник",
  "倒车影像": "Камера заднего вида",
  "360全景影像": "Камера 360 градусов",
  "540全景影像": "Камера 540 градусов",
  "透明底盘": "Прозрачный капот / обзор под авто",
  "倒车车侧预警系统": "Предупреждение о поперечном движении при выезде задним ходом",
  "倒车动态提醒系统": "Динамические подсказки при парковке",
  "自动泊车": "Автоматическая парковка",
  "遥控泊车": "Дистанционная парковка",
  "记忆泊车": "Парковка по памяти",
  "陡坡缓降": "Помощь при спуске с горы",
  "可变悬架": "Адаптивная подвеска",
  "空气悬架": "Пневмоподвеска",
  "可调悬架软硬": "Регулировка жесткости подвески",
  "可调悬架高低": "Регулировка высоты подвески",
  "电动助力转向": "Электроусилитель руля",
  "多功能方向盘": "Многофункциональный руль",
  "方向盘换挡": "Подрулевые лепестки",
  "方向盘电动调节": "Электрорегулировка руля",
  "方向盘记忆": "Память настроек руля",
  "方向盘加热": "Подогрев руля",
  "方向盘加热功能": "Подогрев руля",
  "无钥匙进入": "Бесключевой доступ",
  "无钥匙进入系统": "Система бесключевого доступа",
  "无钥匙启动": "Запуск двигателя кнопкой",
  "无钥匙启动系统": "Система запуска кнопкой",
  "远程启动": "Дистанционный запуск двигателя",
  "自动驻车": "Автоудержание (Auto Hold)",
  "电子驻车": "Электронный стояночный тормоз",
  "全景天窗": "Панорамная крыша",
  "全景天窗可开启": "Открывающаяся панорамная крыша",
  "电动天窗": "Электролюк",
  "不可开启全景天窗": "Панорамная крыша (неоткрывающаяся)",
  "电动后备厢": "Электропривод багажника",
  "感应后备厢": "Багажник с бесконтактным открытием",
  "电动后备厢位置记忆": "Память высоты открытия багажника",
  "车顶行李架": "Рейлинги на крыше",
  "隐私玻璃": "Тонированные задние стекла",
  "后排侧隐私玻璃": "Задние боковые тонированные стекла",
  "电吸门": "Доводчики дверей",
  "电动侧滑门": "Электропривод сдвижных дверей",
  "自动头灯": "Автоматическое включение фар",
  "自动大灯": "Автоматический свет",
  "LED大灯": "Светодиодные фары",
  "矩阵式大灯": "Матричные фары",
  "自适应远近光": "Адаптивный дальний/ближний свет",
  "大灯高度可调": "Регулировка высоты фар",
  "大灯清洗装置": "Омыватель фар",
  "日间行车灯": "Дневные ходовые огни",
  "转向辅助灯": "Подсветка поворотов",
  "车内氛围灯": "Атмосферная подсветка салона",
  "多色氛围灯": "Многоцветная подсветка салона",
  "座椅加热": "Подогрев сидений",
  "前排座椅加热": "Подогрев передних сидений",
  "后排座椅加热": "Подогрев задних сидений",
  "座椅通风": "Вентиляция сидений",
  "前排座椅通风": "Вентиляция передних сидений",
  "后排座椅通风": "Вентиляция задних сидений",
  "前排座椅按摩": "Массаж передних сидений",
  "后排座椅按摩": "Массаж задних сидений",
  "主驾驶座电动调节": "Электрорегулировка сиденья водителя",
  "副驾驶座电动调节": "Электрорегулировка сиденья пассажира",
  "主驾驶座椅记忆": "Память сиденья водителя",
  "副驾驶座椅记忆": "Память сиденья пассажира",
  "第二排座椅电动调节": "Электрорегулировка сидений второго ряда",
  "第二排座椅加热": "Подогрев сидений второго ряда",
  "第二排座椅通风": "Вентиляция сидений второго ряда",
  "第二排座椅按摩": "Массаж сидений второго ряда",
  "第三排座椅": "Третий ряд сидений",
  "第三排座椅电动放倒": "Электроскладывание третьего ряда",
  "座椅腰部支撑调节": "Регулировка поясничной поддержки",
  "后排独立座椅": "Раздельные задние сиденья",
  "后排座椅放倒比例": "Складывание заднего ряда по частям",
  "自动空调": "Климат-контроль",
  "自动空调系统": "Система климат-контроля",
  "双区自动空调": "Двухзонный климат-контроль",
  "三区自动空调": "Трехзонный климат-контроль",
  "四区自动空调": "Четырехзонный климат-контроль",
  "后排独立空调": "Раздельный климат для заднего ряда",
  "后排出风口": "Дефлекторы для заднего ряда",
  "车内空气调节/花粉过滤": "Фильтрация воздуха в салоне",
  "车载空气净化器": "Очиститель воздуха в салоне",
  "PM2.5过滤装置": "Фильтр PM2.5",
  "负离子发生器": "Ионизатор воздуха",
  "香氛系统": "Система ароматизации салона",
  "HUD抬头数字显示": "Проекционный дисплей (HUD)",
  "全液晶仪表盘": "Полностью цифровая приборная панель",
  "液晶仪表尺寸": "Размер цифровой приборной панели",
  "中控彩色液晶屏": "Цветной центральный дисплей",
  "中控屏尺寸": "Размер центрального экрана",
  "副驾娱乐屏": "Пассажирский развлекательный экран",
  "后排液晶屏": "Задний развлекательный экран",
  "GPS导航系统": "Навигационная система GPS",
  "导航路况信息显示": "Отображение пробок в навигации",
  "蓝牙/车载电话": "Bluetooth / громкая связь",
  "手机互联/映射": "Интеграция со смартфоном",
  "CarPlay": "Apple CarPlay",
  "CarLife": "Baidu CarLife",
  "OTA升级": "Обновление ПО по воздуху (OTA)",
  "语音识别控制系统": "Система голосового управления",
  "语音助手": "Голосовой ассистент",
  "语音分区域唤醒识别功能": "Раздельная голосовая активация по зонам",
  "手势控制": "Управление жестами",
  "面部识别": "Распознавание лица",
  "车内生物监测": "Мониторинг присутствия в салоне",
  "车联网": "Подключение к интернет-сервисам",
  "车载WiFi": "Бортовой Wi‑Fi",
  "5G网络": "Поддержка 5G",
  "远程控制": "Дистанционное управление через приложение",
  "手机App远程功能": "Удаленные функции через мобильное приложение",
  "手机无线充电": "Беспроводная зарядка смартфона",
  "前排手机无线充电": "Передняя беспроводная зарядка смартфона",
  "后排手机无线充电": "Задняя беспроводная зарядка смартфона",
  "12V电源接口": "Розетка 12V",
  "USB/Type-C接口": "Разъемы USB/Type‑C",
  "220V/230V电源": "Розетка 220/230V",
  "外后视镜电动调节": "Электрорегулировка зеркал",
  "外后视镜加热": "Подогрев наружных зеркал",
  "外后视镜电动折叠": "Электроскладывание наружных зеркал",
  "外后视镜记忆": "Память настроек наружных зеркал",
  "外后视镜自动防眩目": "Автозатемнение наружных зеркал",
  "内后视镜自动防眩目": "Автозатемнение салонного зеркала",
  "雨量感应式雨刷": "Датчик дождя",
  "后雨刷": "Задний стеклоочиститель",
  "后视镜倒车自动下翻": "Автонаклон зеркал при движении задним ходом",
  "自动防眩目": "Автоматическое затемнение зеркал",
  "真皮座椅": "Кожаный салон",
  "仿皮座椅": "Сиденья из экокожи",
  "Alcantara座椅": "Сиденья Alcantara",
  "运动外观套件": "Спортивный внешний пакет",
  "运动风格座椅": "Спортивные сиденья",
  "19英寸轮毂": "19-дюймовые диски",
  "20英寸轮毂": "20-дюймовые диски",
  "21英寸轮毂": "21-дюймовые диски",
  "道路救援服务": "Сервис дорожной помощи"
}
